codeapi/__init__.py
codeapi/client/__init__.py
codeapi/client/_base.cpython-313-x86_64-linux-gnu.so
codeapi/client/_utils.cpython-313-x86_64-linux-gnu.so
codeapi/client/_async/__init__.py
codeapi/client/_async/_app.cpython-313-x86_64-linux-gnu.so
codeapi/client/_async/_cli.cpython-313-x86_64-linux-gnu.so
codeapi/client/_async/_code.cpython-313-x86_64-linux-gnu.so
codeapi/client/_async/_jobs.cpython-313-x86_64-linux-gnu.so
codeapi/client/_async/_mcp.cpython-313-x86_64-linux-gnu.so
codeapi/client/_async/_web.cpython-313-x86_64-linux-gnu.so
codeapi/client/_sync/__init__.py
codeapi/client/_sync/_app.cpython-313-x86_64-linux-gnu.so
codeapi/client/_sync/_cli.cpython-313-x86_64-linux-gnu.so
codeapi/client/_sync/_code.cpython-313-x86_64-linux-gnu.so
codeapi/client/_sync/_jobs.cpython-313-x86_64-linux-gnu.so
codeapi/client/_sync/_mcp.cpython-313-x86_64-linux-gnu.so
codeapi/client/_sync/_web.cpython-313-x86_64-linux-gnu.so
codeapi/types/__init__.py
codeapi/types/_api.py
codeapi/types/_base.py
codeapi/types/_code.py
codeapi/types/_enums.py
codeapi/types/_env.py
codeapi/types/_exc.py
codeapi/types/_job.py
codeapi/types/_json.py
codeapi/types/_stream.py
codeapi/types/_swarm.py
codeapi/types/_time.py
codeapi/types/_zips.py
codeapi_client-0.5.0.dist-info/METADATA
codeapi_client-0.5.0.dist-info/WHEEL
codeapi_client-0.5.0.dist-info/top_level.txt
codeapi_client-0.5.0.dist-info/RECORD
