Metadata-Version: 2.4
Name: codeapi-client
Version: 0.5.0
Summary: CodeAPI Client
Requires-Python: >=3.10
Requires-Dist: aiofiles>=25.1.0
Requires-Dist: fastapi<=0.118.3
Requires-Dist: fastmcp>=2.13.0.2
Requires-Dist: httpx>=0.28.1
Requires-Dist: psutil>=7.1.1
Requires-Dist: pydantic>=2.8.2
Requires-Dist: python-dotenv>=1.2.1
Requires-Dist: strenum>=0.4.15
Requires-Dist: typing-extensions>=4.15.0
